{
  "inputs": [],
  "servers": {
    "github": {
      "type": "http",
      "url": "https://api.githubcopilot.com/mcp/",
      "gallery": true
    },
    "context7": {
      "type": "stdio",
      "command": "/home/sinity/.local/bin/mcp-context7",
      "args": [],
      "gallery": true
    },
    "postgres-local": {
      "type": "stdio",
      "command": "/home/sinity/.local/bin/mcp-postgres",
      "gallery": false
    },
    "Parallel Search MCP": {
      "type": "http",
      "url": "https://search-mcp.parallel.ai/mcp"
    }
  }
}
